bit16alu.v
module alu (
    input  [15:0] a, b,
    input  [2:0]  opcode,
    output reg [16:0] o,
    output reg s, c, p, z
);

always @(*) begin
    c = 0;

    case (opcode)
        3'd0: begin {c, o} = a + b; end
        3'd1: begin {c, o} = a - b; end
        3'd2: begin o = a + 1; end
        3'd3: begin o = a - 1; end
        3'd4: begin o = a & b; end
        3'd5: begin o = a | b; end
        3'd6: begin o = a ^ b; end
        3'd7: begin o = ~a; end
        default: o = 0;
    endcase

    s = o[15];
    z = (o == 0);
    p = ~^o[15:0];
end

endmodule

tb_alu.sv
module tb_alu;
reg clk ;
reg [15:0] a, b;
reg [2:0] opcode;

wire [16:0] o;
wire s, c, p, z;

integer k;

alu a1 (
   
    .a(a),
    .b(b),
    .opcode(opcode),
    .o(o),
    .s(s),
    .c(c),
    .p(p),
    .z(z)
);

initial clk = 1'b0;
always #5 clk = ~clk;

initial begin
    opcode = 000 ; 
    a = 16'd120;
    b = 16'd100;

    for (k = 1; k < 8; k = k + 1) begin
        #10 opcode = k[2:0];
        
    end
end

initial begin
    $monitor("time=%0t opcode=%0d result=%0d carry=%b sign=%b parity=%b zero=%b",
              $time, opcode, o, c, s, p, z);
end

initial begin
    $dumpfile("tb_alu.vcd");
    $dumpvars(0, tb_alu);
end

initial begin
    #200 $finish;
end

endmodule

tb_alu.vcd
$date
	Sun Jan 11 16:17:10 2026
$end
$version
	Icarus Verilog
$end
$timescale
	1s
$end
$scope module tb_alu $end
$var wire 1 ! z $end
$var wire 1 " s $end
$var wire 1 # p $end
$var wire 17 $ o [16:0] $end
$var wire 1 % c $end
$var reg 16 & a [15:0] $end
$var reg 16 ' b [15:0] $end
$var reg 1 ( clk $end
$var reg 3 ) opcode [2:0] $end
$var integer 32 * k [31:0] $end
$scope module a1 $end
$var wire 16 + a [15:0] $end
$var wire 16 , b [15:0] $end
$var wire 3 - opcode [2:0] $end
$var reg 1 % c $end
$var reg 17 . o [16:0] $end
$var reg 1 # p $end
$var reg 1 " s $end
$var reg 1 ! z $end
$upscope $end
$upscope $end
$enddefinitions $end
$comment Show the parameter values. $end
$dumpall
$end
#0
$dumpvars
b11011100 .
b0 -
b1100100 ,
b1111000 +
b1 *
b0 )
0(
b1100100 '
b1111000 &
0%
b11011100 $
0#
0"
0!
$end
#5
1(
#10
1#
b10100 $
b10100 .
0(
b10 *
b1 )
b1 -
#15
1(
#20
0#
b1111001 $
b1111001 .
0(
b11 *
b10 )
b10 -
#25
1(
#30
1#
b1110111 $
b1110111 .
0(
b100 *
b11 )
b11 -
#35
1(
#40
b1100000 $
b1100000 .
0(
b101 *
b100 )
b100 -
#45
1(
#50
0#
b1111100 $
b1111100 .
0(
b110 *
b101 )
b101 -
#55
1(
#60
b11100 $
b11100 .
0(
b111 *
b110 )
b110 -
#65
1(
#70
1#
1"
b11111111110000111 $
b11111111110000111 .
0(
b1000 *
b111 )
b111 -
